salad_cloud_sdk/__init__.py
salad_cloud_sdk/sdk.py
salad_cloud_sdk/sdk_async.py
salad_cloud_sdk/hooks/__init__.py
salad_cloud_sdk/hooks/hook.py
salad_cloud_sdk/models/__init__.py
salad_cloud_sdk/models/axiom_logging_configuration.py
salad_cloud_sdk/models/container.py
salad_cloud_sdk/models/container_configuration.py
salad_cloud_sdk/models/container_configuration_logging.py
salad_cloud_sdk/models/container_group.py
salad_cloud_sdk/models/container_group_collection.py
salad_cloud_sdk/models/container_group_creation_request.py
salad_cloud_sdk/models/container_group_g_rpc_probe.py
salad_cloud_sdk/models/container_group_http_probe_configuration.py
salad_cloud_sdk/models/container_group_instance.py
salad_cloud_sdk/models/container_group_instance_collection.py
salad_cloud_sdk/models/container_group_instance_patch.py
salad_cloud_sdk/models/container_group_instance_status_count.py
salad_cloud_sdk/models/container_group_liveness_probe.py
salad_cloud_sdk/models/container_group_networking_configuration.py
salad_cloud_sdk/models/container_group_patch.py
salad_cloud_sdk/models/container_group_priority.py
salad_cloud_sdk/models/container_group_probe_exec.py
salad_cloud_sdk/models/container_group_probe_http_header.py
salad_cloud_sdk/models/container_group_queue_connection.py
salad_cloud_sdk/models/container_group_readiness_probe.py
salad_cloud_sdk/models/container_group_startup_probe.py
salad_cloud_sdk/models/container_group_state.py
salad_cloud_sdk/models/container_group_status.py
salad_cloud_sdk/models/container_group_tcp_probe.py
salad_cloud_sdk/models/container_groups_quotas.py
salad_cloud_sdk/models/container_logging.py
salad_cloud_sdk/models/container_logging_configuration_http_1.py
salad_cloud_sdk/models/container_logging_configuration_http_2.py
salad_cloud_sdk/models/container_logging_http_compression.py
salad_cloud_sdk/models/container_logging_http_format.py
salad_cloud_sdk/models/container_logging_http_header.py
salad_cloud_sdk-0.9.0a13.dist-info/licenses/LICENSE
salad_cloud_sdk-0.9.0a13.dist-info/METADATA
salad_cloud_sdk-0.9.0a13.dist-info/WHEEL
salad_cloud_sdk-0.9.0a13.dist-info/top_level.txt
salad_cloud_sdk-0.9.0a13.dist-info/RECORD
