Metadata-Version: 2.4
Name: salad-cloud-sdk
Version: 0.9.0a13
Summary: The SaladCloud REST API. Please refer to the [SaladCloud API Documentation](https://docs.salad.com/api-reference) for more details.
License: MIT
Project-URL: Homepage, https://github.com/saladtechnologies/salad-cloud-sdk-python
Project-URL: Documentation, https://docs.salad.com
Project-URL: Repository, https://github.com/SaladTechnologies/salad-cloud-sdk-python.git
Project-URL: Issues, https://github.com/SaladTechnologies/salad-cloud-sdk-python/issues
Classifier: Development Status :: 3 - Alpha
Classifier: Intended Audience :: Developers
Classifier: License :: OSI Approved :: MIT License
Classifier: Operating System :: OS Independent
Classifier: Programming Language :: Python
Classifier: Programming Language :: Python :: 3
Classifier: Programming Language :: Python :: 3 :: Only
Classifier: Programming Language :: Python :: 3.7
Classifier: Programming Language :: Python :: 3.8
Classifier: Programming Language :: Python :: 3.9
Classifier: Programming Language :: Python :: 3.10
Classifier: Programming Language :: Python :: 3.11
Classifier: Programming Language :: Python :: 3.12
Classifier: Topic :: Internet
Classifier: Topic :: Software Development
Classifier: Topic :: Software Development :: Libraries
Requires-Python: >=3.9
License-File: LICENSE
Requires-Dist: requests>=2.31.0
Dynamic: license-file
